cadCAD/__init__.py
cadCAD/types.py
cadCAD/configuration/__init__.py
cadCAD/configuration/utils/__init__.py
cadCAD/configuration/utils/depreciationHandler.py
cadCAD/configuration/utils/policyAggregation.py
cadCAD/configuration/utils/userDefinedObject.py
cadCAD/diagram/__init__.py
cadCAD/diagram/config_diagram.py
cadCAD/engine/__init__.py
cadCAD/engine/execution.py
cadCAD/engine/simulation.py
cadCAD/engine/utils.py
cadCAD/tools/__init__.py
cadCAD/tools/preparation.py
cadCAD/tools/types.py
cadCAD/tools/utils.py
cadCAD/tools/execution/__init__.py
cadCAD/tools/execution/easy_run.py
cadCAD/tools/profiling/__init__.py
cadCAD/tools/profiling/profile_run.py
cadCAD/tools/profiling/visualizations.py
cadCAD/utils/__init__.py
cadCAD/utils/execution.py
cadCAD/utils/jupyter.py
cadCAD/utils/sys_config.py
documentation/__init__.py
documentation/examples/__init__.py
documentation/examples/example_1.py
documentation/examples/historical_state_access.py
documentation/examples/param_sweep.py
documentation/examples/policy_aggregation.py
documentation/examples/sys_model_A.py
documentation/examples/sys_model_AB_exec.py
documentation/examples/sys_model_A_exec.py
documentation/examples/sys_model_B.py
documentation/examples/sys_model_B_exec.py
testing/__init__.py
testing/generic_test.py
testing/results_comparison.py
testing/test_additional_objs.py
testing/test_arg_count.py
testing/test_param_count.py
testing/test_print.py
testing/test_results_signature.py
testing/test_row_count.py
testing/test_runs.py
testing/utils.py
testing/experiments/__init__.py
testing/models/__init__.py
testing/models/param_sweep.py
testing/models/policy_aggregation.py
testing/tests/__init__.py
testing/tests/append_mod_test.py
testing/tests/test_cadCAD_exp.py
testing/tests/test_import_cadCAD_test.py
testing/tests/test_multi_model_row_count.py
testing/tests/test_param_sweep.py
testing/tests/test_policy_aggregation.py
testing/tests/test_run1psub0.py
testing/tests/test_runs_not_zero.py
testing/tests/test_timestep1psub0.py
cadCAD-0.5.3.dist-info/AUTHORS.txt
cadCAD-0.5.3.dist-info/LICENSE.txt
cadCAD-0.5.3.dist-info/METADATA
cadCAD-0.5.3.dist-info/WHEEL
cadCAD-0.5.3.dist-info/top_level.txt
cadCAD-0.5.3.dist-info/RECORD
