Metadata-Version: 2.1
Name: cadCAD
Version: 0.5.3
Summary: cadCAD: a differential games based simulation software package for research, validation, and         Computer Aided Design of economic systems
Home-page: https://github.com/cadCAD-org/cadCAD
Author: cadCAD-org Developers
Author-email: info@block.science
License: LICENSE.txt
Requires-Python: >=3.9.0
License-File: LICENSE.txt
License-File: AUTHORS.txt
Requires-Dist: pandas
Requires-Dist: funcy
Requires-Dist: dill
Requires-Dist: pathos
Requires-Dist: numpy
Requires-Dist: pytz
Requires-Dist: six
Requires-Dist: tqdm
